priceforge/__init__.py
priceforge/api.py
priceforge/utils.py
priceforge/models/__init__.py
priceforge/models/contracts.py
priceforge/pricing/__init__.py
priceforge/pricing/engines/__init__.py
priceforge/pricing/engines/closed_form.py
priceforge/pricing/engines/fourier.py
priceforge/pricing/engines/monte_carlo.py
priceforge/pricing/models/__init__.py
priceforge/pricing/models/black_76.py
priceforge/pricing/models/black_scholes.py
priceforge/pricing/models/heston.py
priceforge/pricing/models/ode_solver.py
priceforge/pricing/models/parameters.py
priceforge/pricing/models/protocol.py
priceforge/pricing/models/trolle_schwartz.py
priceforge-0.1.0.dist-info/LICENSE
priceforge-0.1.0.dist-info/METADATA
priceforge-0.1.0.dist-info/WHEEL
priceforge-0.1.0.dist-info/top_level.txt
priceforge-0.1.0.dist-info/RECORD
